cuta/__init__.py
cuta/api.py
cuta/cli/__init__.py
cuta/cli/main.py
cuta/cli/utils.py
cuta/config.py
cuta/core/__init__.py
cuta/core/app.py
cuta/core/builder.py
cuta/core/command.py
cuta/core/envs/__init__.py
cuta/core/envs/env.py
cuta/core/envs/shell.py
cuta/core/envs/utils.py
cuta/core/package.py
cuta/core/tomlfile.py
cuta/template/.cuta/config.yml
cuta/template/.cuta/envs/dev/Dockerfile
cuta/template/.cuta/envs/nodev/Dockerfile
cuta/template/.cuta/resources/function.tf
cuta/template/app/__init__.py
cuta/template/app/app.py
cuta-0.1.6.dist-info/entry_points.txt
cuta-0.1.6.dist-info/WHEEL
cuta-0.1.6.dist-info/METADATA
cuta-0.1.6.dist-info/RECORD
