Metadata-Version: 2.1
Name: cuta
Version: 0.1.6
Summary: 
Home-page: https://github.com/ylathouris/cuta
License: MIT
Keywords: serverless,devx
Author: Yani Lathouris
Author-email: ylathouris@gmail.com
Requires-Python: >=3.8,<4.0
Classifier: Development Status :: 3 - Alpha
Classifier: Environment :: Console
Classifier: Intended Audience :: Developers
Classifier: License :: OSI Approved :: MIT License
Classifier: Programming Language :: Python :: 3
Classifier: Programming Language :: Python :: 3.8
Classifier: Topic :: Software Development :: Libraries :: Python Modules
Requires-Dist: colorama (>=0.4.3,<0.5.0)
Requires-Dist: docker (>=4.2.0,<5.0.0)
Requires-Dist: emoji (>=0.5.4,<0.6.0)
Requires-Dist: pyyaml (>=5.3.1,<6.0.0)
Requires-Dist: structlog (>=20.1.0,<21.0.0)
Requires-Dist: toml (>=0.10.1,<0.11.0)
Requires-Dist: typer (>=0.2.1,<0.3.0)
Project-URL: Repository, https://github.com/ylathouris/cuta
